Metadata-Version: 2.1
Name: categorical_finder
Version: 0.0.1
Summary: A Python utility for analyzing and suggesting appropriate encoding methods for categorical columns in CSV datasets.
Home-page: 
Author: Sri Jaya Karti
Author-email: srijayakarti@gmail.com
License: MIT
Keywords: categorical
Classifier: Development Status :: 5 - Production/Stable
Classifier: Intended Audience :: Education
Classifier: Operating System :: Microsoft :: Windows :: Windows 10
Classifier: License :: OSI Approved :: MIT License
Classifier: Programming Language :: Python :: 3
License-File: LICENCE.txt
